{
    "Worlds": 1,
    "Stages": 4,
    "UserClearData": [
        {
            "userClearData": [
                true,
                true,
                true,
                true,
                false,
                false,
                false,
                false,
                false
            ]
        },
        {
            "userClearData": [
                false,
                false,
                false,
                false,
                false,
                false,
                false,
                false,
                false
            ]
        },
        {
            "userClearData": [
                false,
                false,
                false,
                false,
                false,
                false,
                false,
                false,
                false
            ]
        },
        {
            "userClearData": [
                false,
                false,
                false,
                false,
                false,
                false,
                false,
                false,
                false
            ]
        }
    ],
    "UserScoreData": [
        {
            "userScoreData": [
                1,
                1,
                1,
                1,
                0,
                0,
                0,
                0,
                0
            ]
        },
        {
            "userScoreData": [
                0,
                0,
                0,
                0,
                0,
                0,
                0,
                0,
                0
            ]
        },
        {
            "userScoreData": [
                0,
                0,
                0,
                0,
                0,
                0,
                0,
                0,
                0
            ]
        },
        {
            "userScoreData": [
                0,
                0,
                0,
                0,
                0,
                0,
                0,
                0,
                0
            ]
        }
    ]
}